AUTHORS
LICENSE
MANIFEST.in
README.rst
setup.py
multitenancy/__init__.py
multitenancy/admin.py
multitenancy/auth.py
multitenancy/forms.py
multitenancy/middleware.py
multitenancy/models.py
multitenancy/urls.py
multitenancy/views.py
multitenancy/management/__init__.py
multitenancy/management/commands/__init__.py
multitenancy/management/commands/update_backend_links.py
multitenancy/migrations/0001_initial.py
multitenancy/migrations/0002_auto_20141114_1356.py
multitenancy/migrations/0003_auto_20141115_1029.py
multitenancy/migrations/__init__.py
multitenancy/templates/multitenancy/group-detail.html
multitenancy/templates/multitenancy/group-landing.html
multitenancy/templates/multitenancy/tenant-detail.html
multitenancy/tests/__init__.py
multitenancy/tests/mixins.py
multitenancy/tests/test_admin.py
multitenancy/tests/test_auth.py
multitenancy/tests/test_forms.py
multitenancy/tests/test_management.py
multitenancy/tests/test_middleware.py
multitenancy/tests/test_models.py
multitenancy/tests/test_views.py
multitenancy/tests/urls.py
rapidsms_multitenancy.egg-info/PKG-INFO
rapidsms_multitenancy.egg-info/SOURCES.txt
rapidsms_multitenancy.egg-info/dependency_links.txt
rapidsms_multitenancy.egg-info/not-zip-safe
rapidsms_multitenancy.egg-info/requires.txt
rapidsms_multitenancy.egg-info/top_level.txt