Metadata-Version: 1.1
Name: rapidsms-multitenancy
Version: 0.2.0
Summary: Host multiple RapidSMS instances in one project
Home-page: https://github.com/theirc/rapidsms-multitenancy
Author: International Rescue Committee
Author-email: rescuesms-team@caktusgroup.com
License: BSD
Platform: UNKNOWN
Classifier: Topic :: Internet :: WWW/HTTP :: Dynamic Content
Classifier: Intended Audience :: Developers
Classifier: License :: OSI Approved :: BSD License
Classifier: Programming Language :: Python
Classifier: Programming Language :: Python :: 2
Classifier: Programming Language :: Python :: 2.7
Classifier: Programming Language :: Python :: 3
Classifier: Programming Language :: Python :: 3.2
Classifier: Programming Language :: Python :: 3.3
Classifier: Programming Language :: Python :: 3.4
Classifier: Framework :: Django
Classifier: Development Status :: 4 - Beta
Classifier: Operating System :: OS Independent
